tiftool/__init__.py
tiftool/functional.py
tiftool/newfun.py
tiftool/stack.py
tiftool/sub_classes/IndexTracker.py
tiftool/sub_classes/__init__.py
tiftool/tiftool/__init__.py
tiftool/tiftool/functional.py
tiftool/tiftool/stack.py
tiftool/tiftool/sub_classes/IndexTracker.py
tiftool/tiftool/sub_classes/__init__.py
tiftool-0.2.4.dist-info/LICENSE
tiftool-0.2.4.dist-info/METADATA
tiftool-0.2.4.dist-info/WHEEL
tiftool-0.2.4.dist-info/top_level.txt
tiftool-0.2.4.dist-info/RECORD
